zenofai/__init__.py
zenofai/verbose.py
zenofai-0.1.1.dist-info/METADATA
zenofai-0.1.1.dist-info/WHEEL
zenofai-0.1.1.dist-info/top_level.txt
zenofai-0.1.1.dist-info/RECORD
