Metadata-Version: 2.4
Name: zenofai
Version: 0.1.1
Summary: The Zen of GenAI, printed on import
Home-page: https://github.com/anuj-sadani-infrrd/zenofai
Author: Anuj Sadani
Author-email: Anuj Sadani <anuj.sadani3@gmail.com>
License-Expression: MIT
Keywords: AI,Python,Zen,package
Classifier: Programming Language :: Python :: 3
Classifier: Operating System :: OS Independent
Requires-Python: >=3.8
